hl_web3/__init__.py
hl_web3/endpoint.py
hl_web3/exchange.py
hl_web3/info.py
hl_web3/utils/__init__.py
hl_web3/utils/abi_types.py
hl_web3/utils/constants.py
hl_web3/utils/miscs.py
hl_web3/utils/types.py
hl_web3-0.1.1.dist-info/WHEEL
hl_web3-0.1.1.dist-info/METADATA
hl_web3-0.1.1.dist-info/RECORD
