Metadata-Version: 2.3
Name: hl-web3
Version: 0.1.1
Summary: Web3 client for Hyperliquid
Author: Yuki
Author-email: Yuki <oneforalone@gmail.com>
License: MIT License
Requires-Dist: eth-abi>=5.2.0
Requires-Dist: web3>=7.13.0
Requires-Python: >=3.10
Project-URL: Changelog, https://github.com/oneforalone/hl-web3-py/blob/master/CHANGELOG.md
Project-URL: Documentation, https://github.com/oneforalone/hl-web3-py
Project-URL: Homepage, https://github.com/oneforalone/hl-web3-py
Project-URL: Issues, https://github.com/oneforalone/hl-web3-py/issues
Project-URL: Repository, https://github.com/oneforalone/hl-web3-py
